latticeconstructor/__init__.py
latticeconstructor/core.py
latticeconstructor/madx.lark
latticeconstructor/parse.py
latticeconstructor-0.2.5.dist-info/entry_points.txt
latticeconstructor-0.2.5.dist-info/LICENSE
latticeconstructor-0.2.5.dist-info/WHEEL
latticeconstructor-0.2.5.dist-info/METADATA
latticeconstructor-0.2.5.dist-info/RECORD
